pysaga/__init__.py
pysaga/__main__.py
pysaga/commons.py
pysaga/parse_line.py
pysaga/saga.py
pysaga/utils.py
pysaga-0.0.1.dist-info/METADATA
pysaga-0.0.1.dist-info/RECORD
pysaga-0.0.1.dist-info/WHEEL
pysaga-0.0.1.dist-info/top_level.txt
