Metadata-Version: 2.1
Name: pysaga
Version: 0.0.1
Summary: access to french audio saga data
Home-page: https://github.com/aluriak/pysaga
Author: Lucas Bourneuf
Author-email: lucas.bourneuf@laposte.net
License: GPL
Keywords: data,audio,saga
Platform: UNKNOWN
Classifier: Development Status :: 2 - Pre-Alpha
Classifier: License :: OSI Approved :: GNU General Public License (GPL)
Classifier: Natural Language :: English
Classifier: Programming Language :: Python :: 3
Classifier: Programming Language :: Python :: 3.7
Classifier: Topic :: Software Development :: Libraries :: Python Modules
